{
  "_versions": {
    "import-data": 98,
    "generate-entries": 15,
    "export-dashboard": 15,
    "export-analysis": 15,
    "export-companies": 18,
    "export-departments": 18,
    "export-users": 19,
    "manage-user": 25,
    "send-email": 14,
    "export-bank-accounts": 17,
    "export-chart-accounts": 18,
    "export-tga-accounts": 16,
    "chat": 27,
    "audit-log": 21,
    "cleanup-audit-logs": 8,
    "delete-chart-accounts": 7,
    "export-cost-centers": 8,
    "export-mappings": 10
  }
}